<?xml version="1.0" encoding="utf-8" ?>
<dwsync>
<file name="cubrid_forge.php" server="wisetransfers.neelumsoft.com//" local="132568103797338683" remote="132619099200000000" Dst="0" />
<file name="cubrid_driver.php" server="wisetransfers.neelumsoft.com//" local="132568103799972307" remote="132619099200000000" Dst="0" />
<file name="cubrid_result.php" server="wisetransfers.neelumsoft.com//" local="132568103808389540" remote="132619099200000000" Dst="0" />
<file name="cubrid_utility.php" server="wisetransfers.neelumsoft.com//" local="132568103811087057" remote="132619099200000000" Dst="0" />
<file name="index.html" server="wisetransfers.neelumsoft.com//" local="132568103811665367" remote="132619099200000000" Dst="0" />
<file name="cubrid_driver.php" server="roctopus.neelumsoft.com" local="132568103799972307" remote="132636965400000000" Dst="0" />
<file name="cubrid_forge.php" server="roctopus.neelumsoft.com" local="132568103797338683" remote="132636965400000000" Dst="0" />
<file name="cubrid_result.php" server="roctopus.neelumsoft.com" local="132568103808389540" remote="132636965400000000" Dst="0" />
<file name="index.html" server="roctopus.neelumsoft.com" local="132568103811665367" remote="132636965400000000" Dst="0" />
<file name="cubrid_utility.php" server="roctopus.neelumsoft.com" local="132568103811087057" remote="132636965400000000" Dst="0" />
</dwsync>